{
    "ver":1.0,
    "se":{
      "26":{"url":"https://raw.githubusercontent.com/shuming1/teru_f/main/pon_f.wav"},
      "28":{"url":"https://raw.githubusercontent.com/shuming1/teru_f/main/kan_f.wav"},
      "30":{"url":"https://raw.githubusercontent.com/shuming1/teru_f/main/chii_f.m4a"},
      "32":{"url":"https://raw.githubusercontent.com/shuming1/teru_f/main/reach_f.wav"},
      "34":{"url":"https://raw.githubusercontent.com/shuming1/teru_f/main/ron_f.wav"},
      "36":{"url":"https://raw.githubusercontent.com/shuming1/teru_f/main/tsumo_f.wav"}
    }
  }
